{
	"info": {
		"_postman_id": "health-collection-simplified",
		"name": "예약 서비스 - 헬스체크 (간소화)",
		"description": "시스템 상태 모니터링 핵심 API 컬렉션 (GET만 포함)",
		"schema": "https://schema.getpostman.com/json/collection/v2.1.0/collection.json"
	},
	"item": [
		{
			"name": "기본 헬스체크",
			"event": [
				{
					"listen": "test",
					"script": {
						"exec": [
							"pm.test('응답 시간 확인', function () {",
							"    pm.expect(pm.response.responseTime).to.be.below(1000);",
							"});",
							"",
							"pm.test('상태 코드 확인', function () {",
							"    pm.response.to.have.status(200);",
							"});",
							"",
							"pm.test('응답 구조 확인', function () {",
							"    const response = pm.response.json();",
							"    pm.expect(response).to.have.property('status');",
							"    pm.expect(response.status).to.eql('ok');",
							"});"
						],
						"type": "text/javascript"
					}
				}
			],
			"request": {
				"method": "GET",
				"header": [],
				"url": {
					"raw": "{{API_URL}}/health",
					"host": ["{{API_URL}}"],
					"path": ["health"]
				},
				"description": "애플리케이션의 기본 헬스체크 상태를 확인합니다 (인증 불필요)"
			},
			"response": [
				{
					"name": "헬스체크 성공",
					"originalRequest": {
						"method": "GET",
						"header": [],
						"url": {
							"raw": "{{API_URL}}/health",
							"host": ["{{API_URL}}"],
							"path": ["health"]
						}
					},
					"status": "OK",
					"code": 200,
					"_postman_previewlanguage": "json",
					"header": [
						{
							"key": "Content-Type",
							"value": "application/json"
						}
					],
					"cookie": [],
					"body": "{\n    \"status\": \"ok\",\n    \"info\": {\n        \"database\": {\n            \"status\": \"up\"\n        },\n        \"memory_heap\": {\n            \"status\": \"up\"\n        }\n    },\n    \"error\": {},\n    \"details\": {\n        \"database\": {\n            \"status\": \"up\"\n        },\n        \"memory_heap\": {\n            \"status\": \"up\"\n        }\n    }\n}"
				}
			]
		}
	],
	"variable": [
		{
			"key": "API_URL",
			"value": "http://localhost:8000",
			"type": "string"
		}
	]
}